grapl/__init__.py
grapl/admg.py
grapl/algorithms.py
grapl/condind.py
grapl/dsl.py
grapl/eqn.py
grapl/expr.py
grapl/fixtree.py
grapl/util.py
grapl/graphs/back_door.grapl
grapl/graphs/bareinboim_2020.grapl
grapl/graphs/complex_dag.grapl
grapl/graphs/cyclic_graph.grapl
grapl/graphs/front_door.grapl
grapl/graphs/general_scenario.grapl
grapl/graphs/markov1.grapl
grapl/graphs/markov2.grapl
grapl/graphs/napkin.grapl
grapl/graphs/non_identify1.grapl
grapl/graphs/non_identify2.grapl
grapl/graphs/richardson_2017.grapl
grapl/graphs/shpitser_thesis1.grapl
grapl/graphs/shpitser_thesis2.grapl
grapl/graphs/symptoms.grapl
grapl/graphs/tikka_karvanen.grapl
grapl/graphs/topsort_graph.grapl
grapl/ply/__init__.py
grapl/ply/cpp.py
grapl/ply/ctokens.py
grapl/ply/lex.py
grapl/ply/yacc.py
grapl/ply/ygen.py
grapl/test/__init__.py
grapl/test/unit_tests.py
grapl/tutorials/__init__.py
grapl/tutorials/tutorial1.py
grapl/tutorials/tutorial2.py
grapl/tutorials/tutorial3.py
grapl/tutorials/tutorial4.py
grapl/tutorials/tutorial_01.ipynb
grapl/tutorials/tutorial_02.ipynb
grapl/tutorials/tutorial_03.ipynb
grapl/tutorials/tutorial_04.ipynb
grapl/tutorials/tutorial_05.ipynb
grapl/tutorials/tutorial_06.ipynb
grapl_causal-1.6.1.dist-info/LICENSE
grapl_causal-1.6.1.dist-info/METADATA
grapl_causal-1.6.1.dist-info/WHEEL
grapl_causal-1.6.1.dist-info/top_level.txt
grapl_causal-1.6.1.dist-info/RECORD
