Metadata-Version: 2.1
Name: grapl-causal
Version: 1.6.1
Summary: GRAPL: A computational library for nonparametric structural causal modelling, analysis and inference
Home-page: https://github.com/max-little/GRAPL
Author: Max A. Little
Author-email: maxl@mit.edu
License: GNU GPL-3.0
License-File: LICENSE
